aclass/__init__.py
aclass/__main__.py
aclass-0.1.1.dist-info/LICENSE
aclass-0.1.1.dist-info/METADATA
aclass-0.1.1.dist-info/WHEEL
aclass-0.1.1.dist-info/entry_points.txt
aclass-0.1.1.dist-info/top_level.txt
aclass-0.1.1.dist-info/RECORD
