Metadata-Version: 2.1
Name: aclass
Version: 0.1.1
Summary: Online Classes Automation
Home-page: https://github.com/a1eaiactaest/aclass
Author: Piotrek Rybiec
License: MIT
Platform: UNKNOWN
